ttkplus/__init__.py
ttkplus/core/__init__.py
ttkplus/core/create_app.py
ttkplus/core/create_widget.py
ttkplus/core/model.py
ttkplus/core/render.py
ttkplus/logger.py
ttkplus-0.1.9.dist-info/METADATA
ttkplus-0.1.9.dist-info/WHEEL
ttkplus-0.1.9.dist-info/RECORD
