Metadata-Version: 2.1
Name: ttkplus
Version: 0.1.9
Summary: TkinterHelper布局助手 桌面版 官方拓展和工具库
Author: iamxcd
Author-email: iamxcd@gmail.com
Requires-Python: >=3.8,<4.0
Classifier: Programming Language :: Python :: 3
Classifier: Programming Language :: Python :: 3.8
Classifier: Programming Language :: Python :: 3.9
Classifier: Programming Language :: Python :: 3.10
Classifier: Programming Language :: Python :: 3.11
Classifier: Programming Language :: Python :: 3.12
Requires-Dist: pydantic (>=2.10,<3.0)
Requires-Dist: ttkbootstrap (>=1.13.0,<1.14.0)
